fastgrouper/__init__.py
fastgrouper/_core.py
fastgrouper/arr.py
fastgrouper/li.py
fastgrouper/test/__init__.py
fastgrouper/test/test_grouped.py
fastgrouper/test/test_grouped_benchmark.py
fastgrouper-0.1.2.dist-info/LICENSE
fastgrouper-0.1.2.dist-info/METADATA
fastgrouper-0.1.2.dist-info/WHEEL
fastgrouper-0.1.2.dist-info/top_level.txt
fastgrouper-0.1.2.dist-info/RECORD
